setup.cfg
setup.py
grazyna/__init__.py
grazyna/__main__.py
grazyna/auths.py
grazyna/config.py
grazyna/db.py
grazyna/format.py
grazyna/models.py
grazyna/modules.py
grazyna/request.py
grazyna.egg-info/PKG-INFO
grazyna.egg-info/SOURCES.txt
grazyna.egg-info/dependency_links.txt
grazyna.egg-info/not-zip-safe
grazyna.egg-info/requires.txt
grazyna.egg-info/top_level.txt
grazyna/irc/__init__.py
grazyna/irc/client.py
grazyna/irc/exc.py
grazyna/irc/message_controller.py
grazyna/irc/models.py
grazyna/irc/sender.py
grazyna/plugins/__init__.py
grazyna/plugins/admin.py
grazyna/plugins/creeper.py
grazyna/plugins/db.py
grazyna/plugins/github.py
grazyna/plugins/google.py
grazyna/plugins/help.py
grazyna/plugins/hs_wiki.py
grazyna/plugins/lmgtfy.py
grazyna/plugins/onp.py
grazyna/plugins/ping.py
grazyna/plugins/python.py
grazyna/plugins/quotes.py
grazyna/plugins/roll.py
grazyna/plugins/ruletka.py
grazyna/plugins/title.py
grazyna/plugins/weather.py
grazyna/plugins/weekend.py
grazyna/test_mocks/__init__.py
grazyna/test_mocks/dummy_plugin.py
grazyna/test_mocks/importer.py
grazyna/test_mocks/sender.py
grazyna/tests/__init__.py
grazyna/tests/test_client.py
grazyna/tests/test_exc.py
grazyna/tests/test_executed_counter.py
grazyna/tests/test_format.py
grazyna/tests/test_get_args.py
grazyna/tests/test_is_good_cmd.py
grazyna/tests/test_message_controller.py
grazyna/tests/test_module_manager.py
grazyna/tests/test_plugin.py
grazyna/tests/test_request.py
grazyna/tests/test_types.py
grazyna/tests/auths/__init__.py
grazyna/tests/auths/test_abstract_auth.py
grazyna/tests/auths/test_freenode_auth.py
grazyna/tests/auths/test_non_auth.py
grazyna/tests/auths/test_quakenet_auth.py
grazyna/tests/commands/__init__.py
grazyna/tests/commands/base.py
grazyna/tests/commands/test_command_error.py
grazyna/tests/commands/test_command_join.py
grazyna/tests/commands/test_command_kick.py
grazyna/tests/commands/test_command_no_such_nick.py
grazyna/tests/commands/test_command_notice.py
grazyna/tests/commands/test_command_part.py
grazyna/tests/commands/test_command_ping.py
grazyna/tests/commands/test_command_start.py
grazyna/tests/commands/test_command_whois.py
grazyna/utils/__init__.py
