Metadata-Version: 1.1
Name: grazyna
Version: 0.7
Summary: Grazyna The irc bot
Home-page: https://github.com/firemark/grazyna
Author: Firemark
Author-email: marpiechula@gmail.com
License: UNKNOWN
Download-URL: https://github.com/firemark/grazyna/tarball/0.7
Keywords: irc,socket,bot
Platform: UNKNOWN
